[
  {
    "name": "Ember",
    "url": "https://ember-community-slackin.herokuapp.com/"
  },
  {
    "name": "Laravel",
    "url": "https://larachat.co/"
  },
  {
    "name": "Ruby",
    "url": "https://rubydevelopers.typeform.com/to/l7WVWl"
  },
  {
    "name": "Front end",
    "url": "https://frontenddevelopers.org/"
  },
  {
    "name": "Android",
    "url": "https://androidchat.co/"
  },
  {
    "name": "GO",
    "url": "https://docs.google.com/forms/d/e/1FAIpQLScNsNXbz2SCLH5hVNoZS0C70nPAXv730SW9F3K1g6iVvlcUTg/viewform?fbzx=4754263898376949596"
  },
  {
    "name": "PHP Chat",
    "url": "https://phpchat.co"
  },
  {
    "name": "Clojure",
    "url": "http://clojurians.net/"
  },
  {
    "name": "iOS Developers",
    "url": "https://ios-developers.io/"
  },
  {
    "name": "Elixir",
    "url": "https://elixir-slackin.herokuapp.com/"
  },
  {
    "name": "slashrocket",
    "url": "https://slashrocket.io/"
  },
  {
    "name": "Cordova",
    "url": "http://slack.cordova.io/"
  },
  {
    "name": "Python Community",
    "url": "https://pythoncommunity.herokuapp.com/"
  },
  {
    "name": "CFML/ColdFusion",
    "url": "https://cfml-slack.herokuapp.com/"
  },
  {
    "name": "Australia & New Zealand",
    "url": "http://devanz.co"
  },
  {
    "name": "Les Pitonneux",
    "url": "https://pitonneux.slack.com",
    "description": "Montreal QC Canada"
  },
  {
    "name": "Python Brazilian Community",
    "url": "http://slack-pythonbrasil.herokuapp.com/"
  },
  {
    "name": "Remote workers in Romania",
    "url": "weworkremotely.slack.com/"
  },
  {
    "name": "Russian-speaking developers community",
    "url": "https://rusdevs.herokuapp.com/"
  },
  {
    "name": "Kazan Developers",
    "url": "https://devkzn.slack.com/"
  },
  {
    "name": "Polish developers",
    "url": "http://slackin.devstyle.pl/"
  },
  {
    "name": "Spanish-speaking developer communities list",
    "url": "https://github.com/comunidad-tecnologica/awesome-spanish-slack-dev-groups"
  },
  {
    "name": "Ruby Turkey Community",
    "url": "https://rubytr.herokuapp.com/"
  },
  {
    "name": "Rochester NY USA Developers (RocDev)",
    "url": "https://rocdev.org/"
  },
  {
    "name": "Vancouver Developers (yvrdev)",
    "url": "https://yvrdev.slack.com/"
  },
  {
    "name": "Sketch",
    "url": "http://teamsketch.io/"
  },
  {
    "name": "Design Talks",
    "url": "https://docs.google.com/forms/d/e/1FAIpQLSeKT_LC8kKTzJ4JjmgVQVpfl24i1qBkjJ7TYyQcNHL7fBQkYQ/viewform?c=0&w=1"
  },
  {
    "name": "Designer Hangout",
    "url": "https://www.designerhangout.co/"
  },
  {
    "name": "WordPress",
    "url": "https://make.wordpress.org/chat/"
  },
  {
    "name": "Chit Chats",
    "url": "http://www.chitchats.co/"
  },
  {
    "name": "The Evangelist Collective",
    "url": "https://github.com/evangelistcollective/"
  },
  {
    "name": "Psychedelic Chat",
    "url": "http://psychedelicchat.com/"
  },
  {
    "name": "LGBTQ in Technology",
    "url": "https://lgbtq.technology/"
  },
  {
    "name": "#Startup",
    "url": "http://startup.chat"
  },
  {
    "name": "Safelight",
    "url": "http://safelight.herokuapp.com/",
    "description": "Photography."
  },
  {
    "name": "DFIR Community",
    "url": "https://rishi28.typeform.com/to/sTbTI8",
    "description": "Information Security."
  },
  {
    "name": "First Contributors",
    "url": "https://firstcontributors.slack.com/join/shared_invite/enQtNjkxNzQwNzA2MTMwLTVhMWJjNjg2ODRlNWZhNjIzYjgwNDIyZWYwZjhjYTQ4OTBjMWM0MmFhZDUxNzBiYzczMGNiYzcxNjkzZDZlMDM#/",
    "description": "Help / mentorship for open source contributors."
  },
  {
    "name": "IT Pro Community",
    "url": "https://www.electric.ai/it-pro-slack",
    "description": "Connect and network with IT practitioners and decision-makers"
  },
  {
    "name": "SaaS Community",
    "url": "https://join.slack.com/t/saas-hgv7803/shared_invite/zt-qwvrywyr-8DmSpEzBiSWD2WQuB9r9pw",
    "description": "Community for SaaS product builders, to discuss the challenges involved."
  },
  {
    "name": "Google Cloud Platform",
    "url": "http://bit.ly/gcp-slack"
  },
  {
    "name": "Kubernetes",
    "url": "http://slack.kubernetes.io/"
  },
  {
    "name": "DevOps",
    "url": "https://devopschat.co/"
  },
  {
    "name": "Devop Engineers",
    "url": "https://www.devopsengineers.com/"
  },
  {
    "name": "SweetOps",
    "url": "https://slack.cloudposse.com/"
  },
  {
    "name": "Awesome Community",
    "url": "https://github.com/phpearth/awesome-community"
  }
]
