[
  {
    "name": "Go Developer Roadmap",
    "url": "https://github.com/Alikhll/golang-developer-roadmap",
    "description": "Roadmap to becoming a Go developer in 2020 ."
  },
  {
    "name": "Java Developer Roadmap",
    "url": "https://github.com/s4kibs4mi/java-developer-roadmap",
    "description": "Roadmap to becoming a Java developer in 2019 ."
  },
  {
    "name": "Rust Web Developer Roadmap",
    "url": "https://github.com/anshulrgoyal/rust-web-developer-roadmap",
    "description": "Roadmap to becoming a Rust Web developer in 2020 ."
  },
  {
    "name": "Nodejs Developer Roadmap",
    "url": "https://github.com/aliyr/Nodejs-Developer-Roadmap",
    "description": "A Developer Roadmap to becoming a Node.js developer in 2019 ."
  },
  {
    "name": "Developer Roadmap",
    "url": "https://github.com/kamranahmedse/developer-roadmap",
    "description": "Roadmap to becoming a Web Developer in 2020 ."
  },
  {
    "name": "React Developer Roadmap",
    "url": "https://github.com/adam-golab/react-developer-roadmap",
    "description": "Roadmap to becoming a React developer in 2019 ."
  },
  {
    "name": "Angular Developer Roadmap",
    "url": "https://github.com/sulco/angular-developer-roadmap",
    "description": "To collect the most common / important concepts one should learn to become an Angular developer."
  },
  {
    "name": "Vue Developer Roadmap",
    "url": "https://github.com/flaviocopes/vue-developer-roadmap",
    "description": "Roadmap to becoming a Vue.js developer in 2018."
  },
  {
    "name": "ASP.Net Core Developer Roadmap",
    "url": "https://github.com/MoienTajik/AspNetCore-Developer-Roadmap",
    "description": "Roadmap to becoming an ASP .NET Core developer in 2019 ."
  },
  {
    "name": "Laravel Developer Roadmap",
    "url": "https://github.com/Hasnayeen/laravel-developer-roadmap",
    "description": "Roadmap to becoming an Laravel developer in 2020 ."
  },
  {
    "name": "iOS Developer Roadmap",
    "url": "https://github.com/BohdanOrlov/iOS-Developer-Roadmap",
    "description": "Roadmap to becoming an iOS developer in 2018."
  },
  {
    "name": "Android Developer Roadmap",
    "url": "https://github.com/anacoimbrag/android-developer-roadmap",
    "description": "Help new developers to start building beautiful android applications ."
  },
  {
    "name": "Flutter Developer Roadmap",
    "url": "https://github.com/olexale/flutter_roadmap",
    "description": "Roadmap to create hybrid apps using Google's Flutter SDK"
  },
  {
    "name": "Game Developer Roadmap",
    "url": "https://github.com/utilForever/game-developer-roadmap",
    "description": "Roadmap to becoming a game developer in 2020 ."
  },
  {
    "name": "Game Programmer",
    "url": "https://github.com/miloyip/game-programmer",
    "description": "A Study Path for Game Programmer."
  },
  {
    "name": "AI Expert Roadmap",
    "url": "https://github.com/AMAI-GmbH/AI-Expert-Roadmap",
    "description": "Roadmap to becoming an Artificial Intelligence Expert"
  },
  {
    "name": "NLP Roadmap",
    "url": "https://github.com/graykode/nlp-roadmap",
    "description": "ROADMAP and KEYWORD for students those who have interest in learning NLP ."
  },
  {
    "name": "Deep Learning Papers Reading Roadmap",
    "url": "https://github.com/floodsung/Deep-Learning-Papers-Reading-Roadmap",
    "description": "Deep Learning papers reading roadmap for anyone who are eager to learn this amazing tech."
  },
  {
    "name": "Deep Learning Roadmap",
    "url": "https://github.com/machinelearningmindset/deep-learning-roadmap",
    "description": "All You Need to Know About Deep Learning - A kick-starter."
  },
  {
    "name": "Data Scientist Roadmap",
    "url": "https://github.com/hasbrain/data-science-roadmap",
    "description": "Gives you an overview of the core skills needed in data science."
  },
  {
    "name": "Data-scientist-roadmap",
    "url": "https://github.com/MrMimic/data-scientist-roadmap",
    "description": "Bunch of tutorials helping whoever wants to start learning stuff about data science."
  },
  {
    "name": "Data Engineer Roadmap",
    "url": "https://github.com/datastacktv/data-engineer-roadmap",
    "description": "Roadmap to becoming a data engineer in 2020 ."
  },
  {
    "name": "UI/UX Designer Roadmap",
    "url": "https://github.com/togiberlin/ui-ux-designer-roadmap",
    "description": "Roadmap on becoming a UI/UX designer in 2017."
  },
  {
    "name": "Hacker Roadmap",
    "url": "https://github.com/Sundowndev/hacker-roadmap",
    "description": "A guide for amateurs pen testers and a collection of hacking tools, resources and references."
  },
  {
    "name": "The Full-Stack Software Design and Architecture Roadmap",
    "url": "https://github.com/stemmlerjs/software-design-and-architecture-roadmap",
    "description": "A software design and architecture roadmap for any developer."
  },
  {
    "name": "Software architect roadmap",
    "url": "https://github.com/AlaaAttya/software-architect-roadmap",
    "description": "A broadway roadmap that you can follow to start being a software architect."
  },
  {
    "name": "A Roadmap To Become A Better Android Developer",
    "url": "https://medium.com/mindorks/a-roadmap-to-become-a-better-android-developer-3038cf7f8c8d",
    "description": "A collection of articles to provide a proper roadmap to become a better Android Developer."
  }
]
