[
  {
    "name": "anim9",
    "url": "https://github.com/excessive/anim9",
    "description": "3D skeletal animation library (design to be used with IQM and IQE)"
  },
  {
    "name": "bump-3dpd",
    "url": "https://github.com/oniietzschan/bump-3dpd",
    "description": "A 3D collision detection library for Lua."
  },
  {
    "name": "IQE",
    "url": "https://github.com/excessive/iqe",
    "description": "Inter-Quake Export loader (text)"
  },
  {
    "name": "IQM",
    "url": "https://github.com/excessive/iqm",
    "description": "Inter-Quake Model loader (binary)"
  },
  {
    "name": "LÖVE3D",
    "url": "https://github.com/excessive/love3d",
    "description": "3D extensions to LÖVE"
  },
  {
    "name": "Lovox",
    "url": "https://github.com/tjakka5/Lovox",
    "description": "Pseudo-3D library for working with voxels"
  },
  {
    "name": "Brinevector3D",
    "url": "https://github.com/flamendless/brinevector3D",
    "description": "FFI-enabled vector library for 3D (x,y,z)"
  },
  {
    "name": "Jumper",
    "url": "https://github.com/Yonaba/Jumper",
    "description": "Grid-based pathfinding library"
  },
  {
    "name": "andross",
    "url": "https://github.com/pfirsich/andross",
    "description": "a Lua library for 2D skeletal/bone animations with a Löve backend"
  },
  {
    "name": "anim8",
    "url": "https://github.com/kikito/anim8",
    "description": "Animation library"
  },
  {
    "name": "chiro",
    "url": "https://github.com/bjornbytes/chiro",
    "description": "Convenience wrapper around Spine"
  },
  {
    "name": "Peachy",
    "url": "https://github.com/josh-perry/peachy",
    "description": "A parser/renderer for Aseprite animations in LÖVE"
  },
  {
    "name": "skeletor",
    "url": "https://github.com/pelevesque/skeletor",
    "description": "2D skeletal animation system"
  },
  {
    "name": "Walt",
    "url": "https://github.com/davisdude/Walt",
    "description": "Animation library"
  },
  {
    "name": "Lump",
    "url": "https://github.com/sixFingers/lump",
    "description": "Adobe Flash animation runtime"
  },
  {
    "name": "Brady",
    "url": "https://github.com/davisdude/Brady",
    "description": "Camera library with parallax scrolling"
  },
  {
    "name": "Editgrid",
    "url": "https://github.com/bakpakin/Editgrid",
    "description": "Gamera and HUMP compatible scaling grid"
  },
  {
    "name": "gamera",
    "url": "https://github.com/kikito/gamera",
    "description": "Camera system"
  },
  {
    "name": "hump.camera",
    "url": "http://hump.readthedocs.io/en/latest/camera.html",
    "description": "Camera library with window locking and smooth camera movement interpolation"
  },
  {
    "name": "STALKER-X",
    "url": "https://github.com/SSYGEN/STALKER-X",
    "description": "STALKER-X is a camera module for LÖVE"
  },
  {
    "name": "FPSGraph",
    "url": "https://github.com/icrawler/FPSGraph",
    "description": "Small FPS graphing utility"
  },
  {
    "name": "debugGraph",
    "url": "https://github.com/Mechazawa/Love-Debug-Graph",
    "description": "Small OO FPS graphing utillity based on FPSGraph"
  },
  {
    "name": "Lovebird",
    "url": "https://github.com/rxi/lovebird",
    "description": "Browser-based debug console"
  },
  {
    "name": "LoveDebug",
    "url": "https://github.com/Ranguna/LOVEDEBUG",
    "description": "Inline console-like debugger utility"
  },
  {
    "name": "lurker",
    "url": "https://github.com/rxi/lurker",
    "description": "Auto-swaps changed Lua files in a running game"
  },
  {
    "name": "LÖVE API",
    "url": "https://github.com/love2d-community/love-api",
    "description": "The complete API documentation of LÖVE in a Lua table"
  },
  {
    "name": "MakeLove",
    "url": "https://github.com/instilledbee/MakeLove",
    "description": "Automated build creation for your projects, by monitoring changes in real-time (Windows Only)"
  },
  {
    "name": "draft",
    "url": "https://github.com/pelevesque/draft",
    "description": "A module for drawing complex shapes"
  },
  {
    "name": "Artal",
    "url": "https://github.com/unXedDani/Artal",
    "description": "A .PSD parsing library for LÖVE"
  },
  {
    "name": "Autobatch",
    "url": "https://github.com/rxi/autobatch",
    "description": "Small LÖVE module to automate the use of SpriteBatches"
  },
  {
    "name": "HSLUV",
    "url": "https://github.com/hsluv/hsluv-lua",
    "description": "Lua implementation of HSLuv (a human-friendly alternative to HSL)"
  },
  {
    "name": "Maid64",
    "url": "https://github.com/adekto/maid64",
    "description": "Low resolution scaler for LÖVE"
  },
  {
    "name": "Möan.lua",
    "url": "https://github.com/twentytwoo/Moan.lua",
    "description": "Multiple-choice VN-esque messagebox library for LÖVE"
  },
  {
    "name": "renderplanet",
    "url": "https://github.com/meric/renderplanet/",
    "description": "realistic orthographic planet rendering"
  },
  {
    "name": "Sölar",
    "url": "https://github.com/JanWerder/soelar",
    "description": "a fairly simple solar system simulator"
  },
  {
    "name": "svglover",
    "url": "https://github.com/globalcitizen/svglover",
    "description": "Library to import and display simple SVGs in LÖVE"
  },
  {
    "name": "Tove2d",
    "url": "https://github.com/poke1024/tove2d",
    "description": "Animated vector graphics for LÖVE"
  },
  {
    "name": "deep",
    "url": "https://github.com/Nikaoto/deep",
    "description": "Adds Z axis; allows you to queue actions and draw calls"
  },
  {
    "name": "adorbs",
    "url": "https://github.com/JosephShering/adorbs",
    "description": "Minimal, Functional Entity Component System"
  },
  {
    "name": "knife.system",
    "url": "https://github.com/airstruck/knife/blob/master/readme/system.md",
    "description": "Minimalist functional ECS"
  },
  {
    "name": "nata",
    "url": "https://github.com/tesselode/nata",
    "description": "Hybrid OOP/ECS entity management"
  },
  {
    "name": "tiny-ecs",
    "url": "https://github.com/bakpakin/tiny-ecs",
    "description": "Entity Component System for Lua that's simple, flexible, and useful"
  },
  {
    "name": "astray",
    "url": "https://github.com/SiENcE/astray",
    "description": "Astray is a lua based maze, room and dungeon generation library for dungeon crawlers and roguelike video games"
  },
  {
    "name": "cartographer",
    "url": "https://github.com/tesselode/cartographer",
    "description": "Small Tiled map loader and drawer."
  },
  {
    "name": "hump",
    "url": "https://github.com/vrld/hump",
    "description": "Collection of tools for developing games with LÖVE (Gamestates, Timers/Tweens, Vectors, Classes, Signals, Cameras)"
  },
  {
    "name": "knife",
    "url": "https://github.com/airstruck/knife",
    "description": "Collection of useful micro-modules for Lua (Class, State Machines, Bind, Chain, Coroutines, Event, Memoize, Entity, Tests, Timer)"
  },
  {
    "name": "lovely-windows",
    "url": "https://github.com/flamendless/lovely-windows",
    "description": "A Window/Screen Manager Module for virtual windows."
  },
  {
    "name": "love-state-switcher",
    "url": "https://github.com/nekromoff/love-state-switcher",
    "description": "State switcher class for Lua LÖVE Engine"
  },
  {
    "name": "lue",
    "url": "https://github.com/Ulydev/lue",
    "description": "lue is a LÖVE library that allows you to display hue color effects in your game"
  },
  {
    "name": "lume",
    "url": "https://github.com/rxi/lume/",
    "description": "Collection of functions for Lua, geared towards game development"
  },
  {
    "name": "rotLove",
    "url": "https://github.com/paulofmandown/rotLove",
    "description": "Roguelike Toolkit in Love. A Love2D/lua port of rot.js"
  },
  {
    "name": "ScreenManager",
    "url": "https://github.com/rm-code/screenmanager",
    "description": "Screen/State Management for the LÖVE framework"
  },
  {
    "name": "shack",
    "url": "https://github.com/Ulydev/shack",
    "description": "shack is a LÖVE library that lets you easily add screen effects such as shake and rotation"
  },
  {
    "name": "Simple Tiled Implementation",
    "url": "https://github.com/karai17/Simple-Tiled-Implementation",
    "description": "Tiled map loader and renderer"
  },
  {
    "name": "Vivid",
    "url": "https://github.com/WetDesertRock/vivid",
    "description": "Color math, manipulation and conversion library"
  },
  {
    "name": "baton",
    "url": "https://github.com/tesselode/baton",
    "description": " Input library for LÖVE that bridges the gap between keyboard and gamepad controls"
  },
  {
    "name": "boipushy",
    "url": "https://github.com/SSYGEN/boipushy",
    "description": "A simple and easy to use input handler"
  },
  {
    "name": "love-microphone",
    "url": "https://github.com/LPGhatguy/love-microphone",
    "description": "Simple microphone support for LÖVE"
  },
  {
    "name": "tactile",
    "url": "https://github.com/tesselode/tactile",
    "description": "A straightforward and flexible input library"
  },
  {
    "name": "Shädows",
    "url": "https://github.com/matiasah/shadows",
    "description": "A Shadows & Lights engine for löve"
  },
  {
    "name": "Light World",
    "url": "https://github.com/tanema/light_world.lua",
    "description": "A lighting model"
  },
  {
    "name": "Simple Love Lights",
    "url": "https://github.com/dylhunn/simple-love-lights",
    "description": "A very simple raycasting light implementation"
  },
  {
    "name": "Bresenham",
    "url": "https://github.com/rm-code/Bresenham",
    "description": "Bresenham's line algorithm written in Lua"
  },
  {
    "name": "brinevector",
    "url": "https://github.com/novemberisms/brinevector",
    "description": "Standalone lightweight luajit ffi-accelerated 2D vector library for great performance"
  },
  {
    "name": "Cirno's Perfect Math Library",
    "url": "https://github.com/excessive/cpml",
    "description": "Math/intersection library designed for games"
  },
  {
    "name": "delaunay",
    "url": "https://github.com/Yonaba/delaunay",
    "description": "Delaunay triangulation for convex polygons"
  },
  {
    "name": "hump.vector",
    "url": "http://hump.readthedocs.io/en/latest/vector.html",
    "description": "Powerful 2D vector class"
  },
  {
    "name": "MLib",
    "url": "https://github.com/davisdude/mlib",
    "description": "Math and shape-intersection detection library written in Lua. It's aim is to be robust and easy to use"
  },
  {
    "name": "shash",
    "url": "https://github.com/rxi/shash",
    "description": "A simple, lightweight spatial hash for Lua"
  },
  {
    "name": "denver",
    "url": "https://github.com/superzazu/denver.lua",
    "description": "A Löve custom waveform generation library"
  },
  {
    "name": "lovebpm",
    "url": "https://github.com/rxi/lovebpm",
    "description": "A LÖVE library for syncing events to the BPM of an audio track"
  },
  {
    "name": "wave",
    "url": "https://github.com/Ulydev/wave",
    "description": "A sound manager with audio parsing and rhythm functionalities"
  },
  {
    "name": "Grease",
    "url": "https://github.com/bartbes/love-misc-libs/tree/master/grease",
    "description": "Networking library intended to make networking easy for lovers (TCP, UDP, Enet)  [IPv6]"
  },
  {
    "name": "LoverNet",
    "url": "https://github.com/josefnpat/LoverNet",
    "description": "A networking library that leverages bitser and enet [IPv4]"
  },
  {
    "name": "NoobHub",
    "url": "https://github.com/Overtorment/NoobHub",
    "description": "OpenSource multiplayer and network messaging [IPv6]"
  },
  {
    "name": "Sock.lua",
    "url": "https://github.com/camchenry/sock.lua",
    "description": "A Lua networking library for LÖVE games [IPv4]"
  },
  {
    "name": "löve-ws",
    "url": "https://github.com/holywyvern/love-ws",
    "description": "A websocket client and server library"
  },
  {
    "name": "30log",
    "url": "https://github.com/Yonaba/30log",
    "description": "Minified framework for object-orientation in Lua. It features named (and unnamed) classes, single inheritance and a basic support for mixins"
  },
  {
    "name": "classic",
    "url": "https://github.com/rxi/classic/",
    "description": "Tiny class module for Lua. Attempts to stay simple and provide decent performance by avoiding unnecessary over-abstraction"
  },
  {
    "name": "hump.class",
    "url": "http://hump.readthedocs.io/en/latest/class.html",
    "description": "Small, fast class/prototype implementation with multiple inheritance (class-commons)"
  },
  {
    "name": "knife.base",
    "url": "https://github.com/airstruck/knife/blob/master/readme/base.md",
    "description": "Extremely minimal base class providing single inheritance and constructors."
  },
  {
    "name": "middleclass",
    "url": "https://github.com/kikito/middleclass",
    "description": "Simple OOP library for Lua; has inheritance, metamethods (operators), class variables and weak mixin support (class-commons)"
  },
  {
    "name": "jprof",
    "url": "https://github.com/pfirsich/jprof",
    "description": "Profiling library/tool for LÖVE"
  },
  {
    "name": "Piefiller",
    "url": "https://github.com/Polynominal/Piefiller",
    "description": "Graphical profiler for LÖVE"
  },
  {
    "name": "profile.lua",
    "url": "https://bitbucket.org/itraykov/profile.lua/src/",
    "description": "Profile.lua is a small, non-intrusive module for finding bottlenecks in your Lua code"
  },
  {
    "name": "ProFi",
    "url": "https://gist.github.com/rm-code/383c98a6af04652ed9f39b7ae536bcc5",
    "description": "A simple lua profiler that works with LuaJIT and prints a pretty report file in columns"
  },
  {
    "name": "Bump",
    "url": "https://github.com/kikito/bump.lua",
    "description": "Collision detection library for Lua"
  },
  {
    "name": "HC",
    "url": "http://hc.readthedocs.io/en/latest/",
    "description": "Collision detection with arbitrary polygons; allows rotation of objects"
  },
  {
    "name": "loveblobs",
    "url": "https://github.com/exezin/loveblobs",
    "description": "A softbody library with support for both dynamic and static arbitrary softbodies."
  },
  {
    "name": "Windfield",
    "url": "https://github.com/SSYGEN/windfield",
    "description": "Physics module wrapper for LÖVE"
  },
  {
    "name": "LoveDos",
    "url": "https://github.com/rxi/lovedos",
    "description": "A Lua framework for 2D DOS games, implementing a subset of the LÖVE API"
  },
  {
    "name": "LoveFTW",
    "url": "https://bitbucket.org/T-BoneISS/l-veftw",
    "description": "Work-in-progress port to Windows phone 8.1"
  },
  {
    "name": "LovePotion",
    "url": "https://github.com/videah/LovePotion",
    "description": "Unofficial work-in-progress implementation of the LÖVE API for 3DS Homebrew"
  },
  {
    "name": "Love.js",
    "url": "https://github.com/TannerRogalsky/love.js",
    "description": "LÖVE ported to the web using Emscripten"
  },
  {
    "name": "LÖVR",
    "url": "https://github.com/bjornbytes/lovr",
    "description": "LÖVE for virtual reality devices"
  },
  {
    "name": "Love-Snap-Template",
    "url": "https://github.com/popey/love-snap-template",
    "description": "A template for packaging LÖVE games for distribution in the Snappy Store"
  },
  {
    "name": "AppImageKit",
    "url": "https://github.com/AppImage/AppImageKit",
    "description": "Using AppImageKit you can package LÖVE games as AppImages that run on common Linux-based operating systems, such as RHEL, CentOS, Ubuntu, Fedora, debian and derivatives; one game = one file"
  },
  {
    "name": "binser",
    "url": "https://github.com/bakpakin/binser",
    "description": "Customizable Lua Serializer"
  },
  {
    "name": "bitser",
    "url": "https://github.com/gvx/bitser",
    "description": "Serializes and deserializes Lua values with LuaJIT"
  },
  {
    "name": "cdata",
    "url": "https://github.com/excessive/cdata",
    "description": "Serialize between Lua data and C data using LuaJIT's FFI"
  },
  {
    "name": "knife.serialize",
    "url": "https://github.com/airstruck/knife/blob/master/readme/serialize.md",
    "description": "Serialize data as a Lua script"
  },
  {
    "name": "Lady",
    "url": "https://github.com/gvx/Lady",
    "description": "Saving and loading savegames; based on Ser"
  },
  {
    "name": "Ser",
    "url": "https://github.com/gvx/Ser",
    "description": "Fast, robust, richly-featured table serialization library for Lua"
  },
  {
    "name": "Smallfolk",
    "url": "https://github.com/gvx/Smallfolk",
    "description": "A fast, robust, secure, richly-featured table serialization library for Lua"
  },
  {
    "name": "trickle",
    "url": "https://github.com/bjornbytes/trickle",
    "description": "A bitstream library focused on high compression for use in networking"
  },
  {
    "name": "LoveShaderConverter",
    "url": "https://github.com/tsteinholz/LoveShaderConverter",
    "description": "Convert Shadertoy Shader files to LÖVE GLSL Files with handy utilities for infinite purposes"
  },
  {
    "name": "Shadertoy viewer",
    "url": "http://love2d.org/forums/viewtopic.php?f=5&t=80885",
    "description": "Run code copied from shadertoy directly or output the converted code to a LÖVE shader"
  },
  {
    "name": "Moonshine",
    "url": "https://github.com/vrld/moonshine",
    "description": "Repository of common post-processing effects like blur, vignette, color-grading, etc."
  },
  {
    "name": "busted",
    "url": "http://olivinelabs.com/busted/",
    "description": "Simple unit-testing framework with customizable assertions"
  },
  {
    "name": "knife.test",
    "url": "https://github.com/airstruck/knife/blob/master/readme/test.md",
    "description": "Fixture-free test framework"
  },
  {
    "name": "Luassert",
    "url": "https://github.com/Olivine-Labs/luassert",
    "description": "Extends assert() with additional, customizable tests"
  },
  {
    "name": "lua-TestMore",
    "url": "http://fperrad.github.io/lua-TestMore/",
    "description": "Port of Perl's Test::More package"
  },
  {
    "name": "Lunatest",
    "url": "https://github.com/silentbicycle/lunatest",
    "description": "xUnit-style randomized unit testing framework"
  },
  {
    "name": "lust",
    "url": "https://github.com/bjornbytes/lust",
    "description": "Minimal test framework"
  },
  {
    "name": "Specl",
    "url": "http://gvvaughan.github.io/specl/",
    "description": "Behavior Driven Development (BDD) tool"
  },
  {
    "name": "Telescope",
    "url": "http://norman.github.io/telescope/",
    "description": "Highly-customizable BDD-style testing library"
  },
  {
    "name": "Flux",
    "url": "https://github.com/rxi/flux",
    "description": "A fast, lightweight tweening library for Lua"
  },
  {
    "name": "hump.timer",
    "url": "http://hump.readthedocs.io/en/latest/timer.html",
    "description": "Timer and tweening library with flexible tweening methods"
  },
  {
    "name": "knife.timer",
    "url": "https://github.com/airstruck/knife/blob/master/readme/timer.md",
    "description": "Create timers and tweens with ease."
  },
  {
    "name": "tick",
    "url": "https://github.com/rxi/tick",
    "description": "Lua module for delaying function calls"
  },
  {
    "name": "tween.lua",
    "url": "https://github.com/kikito/tween.lua",
    "description": "Tweening/Easing/Interpolating functions for Lua inspired on jQuery's animate method"
  },
  {
    "name": "CatUI",
    "url": "https://github.com/wilhantian/catui",
    "description": "A very light-weight GUI library for LÖVE"
  },
  {
    "name": "GOOi",
    "url": "https://github.com/tavuntu/gooi",
    "description": "Android-oriented GUI library"
  },
  {
    "name": "Gspöt",
    "url": "https://github.com/pgimeno/Gspot",
    "description": "A stateful GUI lib for LÖVE"
  },
  {
    "name": "LoveFrames Fork",
    "url": "https://github.com/unek/LoveFrames/commits/master",
    "description": "0.10 Fork of a GUI library"
  },
  {
    "name": "Love Imgui",
    "url": "https://github.com/slages/love-imgui",
    "description": "imgui module for the LÖVE game engine"
  },
  {
    "name": "Löve-Nuklear",
    "url": "https://github.com/keharriso/love-nuklear",
    "description": "Lightweight immediate mode GUI for LÖVE games"
  },
  {
    "name": "Patchy",
    "url": "https://github.com/excessive/patchy",
    "description": "9patch library"
  },
  {
    "name": "Polywell",
    "url": "https://gitlab.com/technomancy/polywell",
    "description": "A highly-configurable text editor / coding tool written in Lua that runs on the LÖVE game engine."
  },
  {
    "name": "SafeWord",
    "url": "https://github.com/josefnpat/safeword",
    "description": "An overscan detection library for LÖVE"
  },
  {
    "name": "SUIT",
    "url": "https://github.com/vrld/SUIT",
    "description": "small immediate mode GUI library"
  },
  {
    "name": "ListBox",
    "url": "https://github.com/darkmetalic/ListBox",
    "description": "A dynamic ListBox for LÖVE that supports touch, mouse, and keyboard inputs"
  },
  {
    "name": "ArrayRotation",
    "url": "https://gist.github.com/rm-code/4118d4a97d8cde16952199d94b84ead0",
    "description": "Rotation of two dimensional arrays (square and non-square)"
  },
  {
    "name": "cargo",
    "url": "https://github.com/bjornbytes/cargo",
    "description": "Asset manager"
  },
  {
    "name": "chance.lua",
    "url": "http://ejmr.github.io/chance.lua/",
    "description": "Library for generating random data"
  },
  {
    "name": "GifCat",
    "url": "https://github.com/WetDesertRock/GifCat",
    "description": "A simple module for saving gifs from LÖVE"
  },
  {
    "name": "i18n",
    "url": "https://github.com/excessive/i18n",
    "description": "Internationalization library designed to help localize your game"
  },
  {
    "name": "log.lua",
    "url": "https://github.com/rxi/log.lua",
    "description": "Library for configurable log output"
  },
  {
    "name": "love-loader",
    "url": "https://github.com/kikito/love-loader",
    "description": "Threaded resource loading"
  },
  {
    "name": "love2d-assets-loader",
    "url": "https://github.com/Yonaba/love2d-assets-loader",
    "description": "Assets Loader"
  },
  {
    "name": "love-pe",
    "url": "https://github.com/RamiLego4Game/love-pe",
    "description": "A tool made in LÖVE for changing LÖVE icon itself"
  },
  {
    "name": "Lily",
    "url": "https://github.com/MikuAuahDark/lily",
    "description": "Async Asset Loader"
  },
  {
    "name": "Luvent",
    "url": "https://github.com/ejmr/Luvent",
    "description": "Simple event-driven programming"
  },
  {
    "name": "splashy",
    "url": "https://github.com/videah/splashy",
    "description": "Splash Screen Library"
  },
  {
    "name": "tick",
    "url": "https://github.com/bjornbytes/tick",
    "description": "Useful timing tweaks for LÖVE's run loop"
  },
  {
    "name": "SSYGEN's",
    "url": "https://github.com/SSYGEN/blog",
    "description": "A blog by SSYGEN with articles about game development using LÖVE"
  },
  {
    "name": "Using Tiled Maps in LÖVE",
    "url": "http://lua.space/gamedev/using-tiled-maps-in-love",
    "description": "An article about using maps created with Tiled in your LÖVE game"
  },
  {
    "name": "Tutorial on making an Arkanoid-type game",
    "url": "https://github.com/noooway/love2d_arkanoid_tutorial/wiki",
    "description": "A complete tutorial on how to make a breakout clone by nooowaay"
  },
  {
    "name": "Simple Game Tutorials",
    "url": "https://simplegametutorials.github.io/",
    "description": "Tutorials for making simple games with LÖVE (Snake, Sokoban, Tetris, etc.)"
  },
  {
    "name": "How to LÖVE",
    "url": "http://sheepolution.com/learn/book/contents",
    "description": "A book by Sheepolution teaching LÖVE from the ground up"
  },
  {
    "name": "Introduction to Game Development",
    "url": "https://cs50.github.io/games/",
    "description": "Harvard College’s CS50 extension (Spring 2018)"
  },
  {
    "name": "Love-Atom",
    "url": "https://atom.io/packages/love-atom",
    "description": "Smart autocompletion for the LÖVE framework in Atom."
  },
  {
    "name": "Autocomplete GLSL",
    "url": "https://atom.io/packages/autocomplete-glsl",
    "description": "Adds GLSL autocompletion in Atom"
  },
  {
    "name": "language-glsl",
    "url": "https://atom.io/packages/language-glsl",
    "description": "OpenGL Shading Language support in Atom"
  },
  {
    "name": "language-lua",
    "url": "https://atom.io/packages/language-lua",
    "description": "Lua language support in Atom"
  },
  {
    "name": "linter-luacheck",
    "url": "https://github.com/AtomLinter/linter-luacheck",
    "description": "Lint Lua on the fly, using luacheck"
  },
  {
    "name": "Löve Launcher",
    "url": "https://atom.io/packages/love-launcher",
    "description": "Launch LÖVE for the current project without having to leave Atom"
  },
  {
    "name": "Löve IDE",
    "url": "https://atom.io/packages/love-ide",
    "description": "This package auto-installs several utilities for writing Love2D games in Atom"
  },
  {
    "name": "Autocomplete Löve",
    "url": "https://atom.io/packages/autocomplete-love",
    "description": "Auto-complete and snippets for LÖVE"
  },
  {
    "name": "Hyperclick Löve",
    "url": "https://atom.io/packages/hyperclick-love",
    "description": "A Hyperclick provider for LÖVE which shows the wiki"
  },
  {
    "name": "linter-luaparse",
    "url": "https://atom.io/packages/linter-luaparse",
    "description": "Lua syntax error checking in Atom"
  },
  {
    "name": "Lua Syntax Highlighter",
    "url": "https://github.com/ForbesLindesay/brackets-language-extensions",
    "description": "Add Lua syntax highlighting in Brackets"
  },
  {
    "name": "LÖVE Hints for Brackets.io",
    "url": "https://gitlab.com/sdonalcreative/brackets-love-hints/",
    "description": "Provides LÖVE code hints"
  },
  {
    "name": "Run LÖVE",
    "url": "https://github.com/instilledbee/run-love2d",
    "description": "Run LÖVE projects with a hotkey"
  },
  {
    "name": "API Syntax Hightlight",
    "url": "https://github.com/flamendless/LOVE-API-Extractor-for-ZeroBraneStudio",
    "description": "Script to add LOVE API syntax highlighting to ZBS."
  },
  {
    "name": "Lua for IDEA",
    "url": "https://bitbucket.org/sylvanaar2/lua-for-idea/wiki/Home",
    "description": "Lua plugin for IntelliJ-IDEA"
  },
  {
    "name": "LÖVE IDEA",
    "url": "https://github.com/rm-code/love-IDEA-plugin",
    "description": "Snippets and code completion for IntelliJ-IDEA"
  },
  {
    "name": "Vim LOVE Docs",
    "url": "https://github.com/davisdude/vim-love-docs",
    "description": "Syntax highlighting for Vim"
  },
  {
    "name": "LÖVE API for Notepad++",
    "url": "https://github.com/dail8859/love-api-npp",
    "description": "Code completion and documentation for Notepad++"
  },
  {
    "name": "Visual Studio Code LÖVE Launcher",
    "url": "https://marketplace.visualstudio.com/items?itemName=JanW.love-launcher",
    "description": "A Löve Launcher Extension for Visual Studio Code"
  },
  {
    "name": "Lua for Visual Studio Code",
    "url": "https://marketplace.visualstudio.com/items?itemName=trixnz.vscode-lua",
    "description": "Provides Intellisense and Linting for Lua in VSCode"
  },
  {
    "name": "Package Manager",
    "url": "https://packagecontrol.io/",
    "description": "The Sublime Text package manager that makes it exceedingly simple to find, install and keep packages up-to-date."
  },
  {
    "name": "SublimeLove",
    "url": "https://packagecontrol.io/packages/SublimeLove",
    "description": "Supports syntax highlighting, auto-completion, and build system."
  },
  {
    "name": "SublimeLinter-luacheck",
    "url": "https://packagecontrol.io/packages/SublimeLinter-luacheck",
    "description": "Provides linting and static analysis of your Lua code."
  },
  {
    "name": "awesome-lua",
    "url": "https://github.com/LewisJEllis/awesome-lua",
    "description": "A list like this one, but more general and encompassing all of Lua's uses"
  },
  {
    "name": "awesome-love-shaders",
    "url": "https://github.com/karai17/awesome-love-shaders",
    "description": "A collection of shaders designed to work in LÖVE"
  },
  {
    "name": "awesome-pico8",
    "url": "https://github.com/felipebueno/awesome-PICO-8",
    "description": "A curated list of PICO-8 resources, tutorials, tools and more"
  }
]
