[
  {
    "name": "8 Classic Storytelling Techniques for Engaging Presentations",
    "url": "https://www.sparkol.com/en/Blog/8-Classic-storytelling-techniques-for-engaging-presentations",
    "description": "by Ffion Lindsay"
  },
  {
    "name": "Block Your Talk",
    "url": "http://eleganthack.com/block-your-talk/",
    "description": "by Christina Wodtke"
  },
  {
    "name": "How To Get Speaking Engagements",
    "url": "https://www.samjarman.co.nz/blog/speaking-gigs",
    "description": "by Sam Jarman"
  },
  {
    "name": "Nine Secrets to Powerful Public Speaking",
    "url": "http://www.gq-magazine.co.uk/article/public-speaking-tips",
    "description": "by Julian Treasure"
  },
  {
    "name": "Presenting is Performance",
    "url": "http://eleganthack.com/presenting-is-performance/",
    "description": "by Christina Wodtke"
  },
  {
    "name": "Speaker Style Bingo: 10 Presentation Anti-Patterns",
    "url": "http://www.troyhunt.com/2015/06/speaker-style-bingo-10-presentation.html",
    "description": "by Troy Hunt"
  },
  {
    "name": "Some Thoughts On Doing Conference Sessions",
    "url": "http://derickbailey.com/2015/11/11/some-thoughts-on-doing-conference-sessions/",
    "description": "by Derick Bailey"
  },
  {
    "name": "How To Prepare And Write A Tech Conference Talk",
    "url": "http://wunder.schoenaberselten.com/2016/02/16/how-to-prepare-and-write-a-tech-conference-talk/",
    "description": "by Lena Reinhard"
  },
  {
    "name": "Propose, Prepare, Present",
    "url": "http://shop.oreilly.com/product/0636920027096.do",
    "description": "Free Ebook by Alistair Croll (O'Reilly)"
  },
  {
    "name": "Presentation Patterns",
    "url": "http://presentationpatterns.com/",
    "description": "by Neal Ford, Matthew McCullough, and Nate Schutta (Addison-Wesley)"
  },
  {
    "name": "Presentation Zen Design",
    "url": "http://www.amazon.com/gp/product/0321668790",
    "description": "by Garr Reynolds. How to design your presentation."
  },
  {
    "name": "TED Talks: The Official TED Guide to Public Speaking",
    "url": "http://www.amazon.com/d/0544634497/",
    "description": "by Chris Anderson (Houghton Mifflin Harcourt). Start to finish guide to giving powerful talks."
  },
  {
    "name": "Call to Speakers",
    "url": "http://calltospeakers.com/",
    "description": "A list of open applications for conference talks. Get notified of new opportunities via a weekly newsletter, Twitter account, or RSS feed."
  },
  {
    "name": "Callback Women",
    "url": "http://www.callbackwomen.com/",
    "description": "Sharing CFPs via Twitter."
  },
  {
    "name": "PaperCall",
    "url": "https://papercall.io/",
    "description": "Place to manage your talks and submissions."
  },
  {
    "name": "IT CFP List",
    "url": "https://github.com/softwaremill/it-cfp-list",
    "description": "List of IT conferences Call For Papers, changes are also published via Twitter @ItCfpList."
  },
  {
    "name": "Toastmasters",
    "url": "https://www.toastmasters.org/Find-a-Club",
    "description": "An international non-profit educational organizations that facilitates the creation and growth of clubs around the world. The goal of the clubs is to improve the leadership and public speaking skills of members."
  },
  {
    "name": "Awesome",
    "url": "https://github.com/sindresorhus/awesome",
    "description": "A collection of awesome things curated by Sindre Sorhus"
  },
  {
    "name": "Awesome Community",
    "url": "https://github.com/peterkokot/awesome-community",
    "description": "A collection of awesome communities curated by Peter Kokot"
  },
  {
    "name": "Public Speaking",
    "url": "https://github.com/vmbrasseur/Public_Speaking",
    "description": "A collection of resources on presenting at technical conferences by VM Brasseur"
  },
  {
    "name": "The Talk on Talks",
    "url": "http://devslovebacon.com/conferences/bacon-2014/talks/the-talk-on-talks",
    "description": "by Zach Holman [36:26]"
  },
  {
    "name": "10 Quick Tips for More Effective Conference Submissions and Presentations",
    "url": "https://www.youtube.com/watch?v=fJz4JJIchaY",
    "description": "by Matthew McCullough [30:07]"
  },
  {
    "name": "How to Talk to Developers",
    "url": "https://www.youtube.com/watch?v=l9JXH7JPjR4",
    "description": "by Ben Orenstein [47:37]"
  },
  {
    "name": "How to Stay Calm When You Know You'll Be Stressed",
    "url": "https://www.ted.com/talks/daniel_levitin_how_to_stay_calm_when_you_know_you_ll_be_stressed",
    "description": "by Daniel Levitin [12:20]"
  },
  {
    "name": "The surprising secret to speaking with confidence",
    "url": "https://www.youtube.com/watch?v=a2MR5XbJtXU",
    "description": "by Caroline Goyder [18:55]"
  },
  {
    "name": "Bringing Your Full Voice to Life",
    "url": "https://www.youtube.com/watch?v=Ze763kgrWGg",
    "description": " by Barbara McAfee [19:07]"
  },
  {
    "name": "ConferenceList",
    "url": "https://conferencelist.io/",
    "description": "by Cezar Floroiu. A list of conferences around the world."
  },
  {
    "name": "Speaking.io",
    "url": "http://speaking.io",
    "description": "Tips for preparing your talk and get ready to deliver it"
  },
  {
    "name": "awesome-talks",
    "url": "https://github.com/JanVanRyswyck/awesome-talks",
    "description": "a collection of awesome tech talks"
  },
  {
    "name": "We Are All Awesome!",
    "url": "http://weareallaweso.me/",
    "description": "a collection of interesting posts about speaking, preparing, motivation, etc"
  },
  {
    "name": "HelpMeAbstract",
    "url": "http://helpmeabstract.com/",
    "description": "Get feedback from veteran speakers before you submit your talk."
  }
]
