[
  {
    "name": "Google Cloud",
    "url": "https://cloud.google.com/community/"
  },
  {
    "name": "Free Code Camp",
    "url": "https://www.freecodecamp.org/news/a-friendly-introduction-to-kubernetes-670c50ce4542/"
  },
  {
    "name": "Kubernetes Community Overview and Contributions Guide by Ihor Dvoretskyi",
    "url": "https://docs.google.com/presentation/d/1JqcALpsg07eH665ZXQrIvOcin6SzzsIUjMRRVivrZMg/edit?usp=sharing"
  },
  {
    "name": "Are you Ready to Manage your Infrastructure like Google?",
    "url": "http://blog.jetstack.io/blog/k8s-getting-started-part1/"
  },
  {
    "name": "Google is years ahead when it comes to the cloud, but it's happy the world is catching up",
    "url": "http://www.businessinsider.in/Google-is-years-ahead-when-it-comes-to-the-cloud-but-its-happy-the-world-is-catching-up/articleshow/47793327.cms"
  },
  {
    "name": "An Intro to Google’s Kubernetes and How to Use It by Laura Frank",
    "url": "http://www.ctl.io/developers/blog/post/what-is-kubernetes-and-how-to-use-it/"
  },
  {
    "name": "Kubernetes: The Future of Cloud Hosting by Meteorhacks",
    "url": "https://github.com/meteorhacks/meteorhacks.github.io/blob/master/_posts/2015-04-22-learn-kubernetes-the-future-of-the-cloud.md"
  },
  {
    "name": "Kubernetes by Google by Gaston Pantana",
    "url": "http://thevirtualizationguy.wordpress.com/tag/kubernetes/"
  },
  {
    "name": "Key Concepts by Arun Gupta",
    "url": "http://blog.arungupta.me/key-concepts-kubernetes/"
  },
  {
    "name": "Application Containers: Kubernetes and Docker from Scratch by Keith Tenzer",
    "url": "http://keithtenzer.com/2015/06/01/application-containers-kubernetes-and-docker-from-scratch/"
  },
  {
    "name": "Learn the Kubernetes Key Concepts in 10 Minutes by Omer Dawelbeit",
    "url": "http://omerio.com/2015/12/18/learn-the-kubernetes-key-concepts-in-10-minutes/"
  },
  {
    "name": "The Children's Illustrated Guide to Kubernetes by Deis",
    "url": "https://kubernetes.io/blog/2016/06/illustrated-childrens-guide-to-kubernetes/"
  },
  {
    "name": "The ‘kubectl run’ command by Michael Hausenblas",
    "url": "http://medium.com/@mhausenblas/the-kubectl-run-command-27c68de5cb76#.mlwi5an7o"
  },
  {
    "name": "Docker Kubernetes Lab Handbook by Peng Xiao",
    "url": "https://github.com/xiaopeng163/docker-k8s-lab"
  },
  {
    "name": "Curated Resources for Kubernetes",
    "url": "https://hackr.io/tutorials/learn-kubernetes"
  },
  {
    "name": "Kubernetes Comic by Google Cloud Platform",
    "url": "https://cloud.google.com/kubernetes-engine/kubernetes-comic/"
  },
  {
    "name": "Kubernetes 101: Pods, Nodes, Containers, and Clusters by Dan Sanche",
    "url": "https://medium.com/google-cloud/kubernetes-101-pods-nodes-containers-and-clusters-c1509e409e16"
  },
  {
    "name": "An Introduction to Kubernetes by Justin Ellingwood",
    "url": "http://www.digitalocean.com/community/tutorials/an-introduction-to-kubernetes"
  },
  {
    "name": "Kubernetes and everything else",
    "url": "https://rinormaloku.com/introduction-application-architecture/",
    "description": "Introduction to Kubernetes and it's context by Rinor Maloku"
  },
  {
    "name": "Installation on Centos 7",
    "url": "http://severalnines.com/blog/installing-kubernetes-cluster-minions-centos7-manage-pods-services"
  },
  {
    "name": "Setting Up a Kubernetes Cluster on Ubuntu 18.04",
    "url": "https://mherman.org/blog/2018/08/20/setting-up-a-kubernetes-cluster-on-ubuntu/"
  },
  {
    "name": "Cloud Native Landscape",
    "url": "https://landscape.cncf.io/"
  },
  {
    "name": "The Kubernetes Handbook by Farhan Hasin Chowdhury",
    "url": "https://www.freecodecamp.org/news/the-kubernetes-handbook/"
  },
  {
    "name": "Bootstrapping Microservices by Ashley Davis",
    "url": "https://www.manning.com/books/bootstrapping-microservices-with-docker-kubernetes-and-terraform"
  },
  {
    "name": "Kubernetes Native Microservices with Quarkus, and MicroProfile by John Clingan and Ken Finnigan",
    "url": "https://www.manning.com/books/kubernetes-native-microservices-with-quarkus-and-microprofile"
  },
  {
    "name": "How to Deploy a REST API in Kubernetes",
    "url": "https://www.loginradius.com/blog/async/rest-api-kubernetes/"
  }
]
